{
  "type": "object",
  "properties": {
    "name": {
      "type": "string",
      "description": "Short human-readable name for the worktree, e.g. \"fix-login-flow\" or \"desktop-cwd-isolation\". Used to derive the worktree directory and default branch name."
    },
    "branch_name": {
      "type": "string",
      "description": "Optional git branch name to create. If omitted, a unique branch name like letta/<name>-<suffix> is generated."
    },
    "base_ref": {
      "type": "string",
      "description": "Optional git ref to base the worktree on. Defaults to the latest remote default branch, usually origin/main."
    },
    "repo_path": {
      "type": "string",
      "description": "Optional path to the git repository to create the worktree from. Use this when the current conversation cwd is not inside the target repo."
    },
    "refresh_base": {
      "type": "boolean",
      "description": "Whether to fetch the remote base branch before creating the worktree. Defaults to true."
    },
    "switch_cwd": {
      "type": "boolean",
      "description": "Whether to switch this conversation's working directory to the new worktree after creation. Defaults to true."
    }
  },
  "required": ["name"],
  "additionalProperties": false,
  "$schema": "http://json-schema.org/draft-07/schema#"
}
